{
    "os": "Linux-4.15.0-140-generic-x86_64-with-Ubuntu-18.04-bionic",
    "python": "3.6.9",
    "heartbeatAt": "2021-06-12T01:42:29.111543",
    "startedAt": "2021-06-12T01:42:28.010750",
    "docker": null,
    "gpu": "Tesla P100-PCIE-16GB",
    "gpu_count": 2,
    "cpu_count": 32,
    "cuda": "9.2.148.1",
    "args": [
        "--model_name_or_path",
        "bert-large-cased",
        "--input_format",
        "typed_entity_marker",
        "--seed",
        "78",
        "--run_name",
        "bert-large"
    ],
    "state": "running",
    "program": "train_tacred.py",
    "codePath": "train_tacred.py",
    "git": {
        "remote": "https://github.com/wzhouad/RE_improved_baseline.git",
        "commit": "f84ea3b036a5c1526e36e4cafc8ff33267e46a62"
    },
    "email": "majumder.gs@gmail.com",
    "root": "/home/akshay/re_rc/RE_improved_baseline",
    "host": "2teslap100",
    "username": "akshay",
    "executable": "/home/akshay/pyTorch-env/bin/python"
}
